prometheus_client/__init__.py
prometheus_client/asgi.py
prometheus_client/context_managers.py
prometheus_client/core.py
prometheus_client/decorator.py
prometheus_client/exposition.py
prometheus_client/gc_collector.py
prometheus_client/metrics.py
prometheus_client/metrics_core.py
prometheus_client/mmap_dict.py
prometheus_client/multiprocess.py
prometheus_client/parser.py
prometheus_client/platform_collector.py
prometheus_client/process_collector.py
prometheus_client/py.typed
prometheus_client/registry.py
prometheus_client/samples.py
prometheus_client/utils.py
prometheus_client/values.py
prometheus_client/bridge/__init__.py
prometheus_client/bridge/graphite.py
prometheus_client/openmetrics/__init__.py
prometheus_client/openmetrics/exposition.py
prometheus_client/openmetrics/parser.py
prometheus_client/twisted/__init__.py
prometheus_client/twisted/_exposition.py
prometheus_client-0.19.0.dist-info/LICENSE
prometheus_client-0.19.0.dist-info/METADATA
prometheus_client-0.19.0.dist-info/NOTICE
prometheus_client-0.19.0.dist-info/WHEEL
prometheus_client-0.19.0.dist-info/top_level.txt
prometheus_client-0.19.0.dist-info/RECORD
