Metadata-Version: 2.1
Name: prometheus_client
Version: 0.19.0
Summary: Python client for the Prometheus monitoring system.
Home-page: https://github.com/prometheus/client_python
Author: Brian Brazil
Author-email: brian.brazil@robustperception.io
License: Apache Software License 2.0
Keywords: prometheus monitoring instrumentation client
Classifier: Development Status :: 4 - Beta
Classifier: Intended Audience :: Developers
Classifier: Intended Audience :: Information Technology
Classifier: Intended Audience :: System Administrators
Classifier: Programming Language :: Python
Classifier: Programming Language :: Python :: 3
Classifier: Programming Language :: Python :: 3.8
Classifier: Programming Language :: Python :: 3.9
Classifier: Programming Language :: Python :: 3.10
Classifier: Programming Language :: Python :: 3.11
Classifier: Programming Language :: Python :: 3.12
Classifier: Programming Language :: Python :: Implementation :: CPython
Classifier: Programming Language :: Python :: Implementation :: PyPy
Classifier: Topic :: System :: Monitoring
Classifier: License :: OSI Approved :: Apache Software License
Requires-Python: >=3.8
License-File: LICENSE
License-File: NOTICE
Provides-Extra: twisted
Requires-Dist: twisted; extra == "twisted"
